Valuation_API/__init__.py
Valuation_API/valuation_api.py
Valuation_API-0.0.5.dist-info/METADATA
Valuation_API-0.0.5.dist-info/WHEEL
Valuation_API-0.0.5.dist-info/top_level.txt
Valuation_API-0.0.5.dist-info/RECORD
