Metadata-Version: 2.1
Name: Valuation-API
Version: 0.0.5
Summary: Library that allows you to connect to the LVA valuation API
Home-page: UNKNOWN
Author: Cristóbal Scheihing Orrego
Author-email: cristobal.scheihing@lvaindices.com
License: MIT
Platform: UNKNOWN
Requires-Dist: requests (>=2.23.0)
